progstats/__init__.py
progstats/main.py
progstats/router.py
progstats/entities/Project.py
progstats/entities/Topic.py
progstats/entities/__init__.py
progstats/static/logo.png
progstats/static/style.css
progstats/templates/header.html
progstats/templates/home.html
progstats/templates/lister.html
progstats/templates/project.html
progstats/templates/topic.html
progstats-1.2.0.data/scripts/backup.sh
progstats-1.2.0.data/scripts/printenv
progstats-1.2.0.data/scripts/restore.sh
progstats-1.2.0.dist-info/LICENSE
progstats-1.2.0.dist-info/METADATA
progstats-1.2.0.dist-info/WHEEL
progstats-1.2.0.dist-info/top_level.txt
progstats-1.2.0.dist-info/RECORD
