Metadata-Version: 2.1
Name: progstats
Version: 1.2.0
Summary: A website indexing git statistics, code coverage and documentation for programming projects
Home-page: https://gitlab.namibsun.net/namibsun/python/progstats
Author: Hermann Krumrey
Author-email: hermann@krumreyh.com
License: GNU GPL3
Platform: UNKNOWN
Classifier: License :: OSI Approved :: GNU General Public License v3 (GPLv3)
Requires-Dist: flask
Requires-Dist: cheroot
